ginjax/__init__.py
ginjax/data.py
ginjax/models.py
ginjax/utils.py
ginjax/geometric/__init__.py
ginjax/geometric/common.py
ginjax/geometric/constants.py
ginjax/geometric/functional_geometric_image.py
ginjax/geometric/geometric_image.py
ginjax/geometric/multi_image.py
ginjax/ml/__init__.py
ginjax/ml/layers.py
ginjax/ml/losses.py
ginjax/ml/stopping_conditions.py
ginjax/ml/training.py
ginjax-0.1.6.dist-info/METADATA
ginjax-0.1.6.dist-info/WHEEL
ginjax-0.1.6.dist-info/licenses/LICENSE
ginjax-0.1.6.dist-info/RECORD
