Metadata-Version: 2.4
Name: ginjax
Version: 0.1.6
Summary: Package for building Convolutional Neural Networks on images of tensors.
License: MIT License
License-File: LICENSE
Requires-Python: >=3.10
Requires-Dist: equinox>=0.11.11
Requires-Dist: imageio>=2.37.0
Requires-Dist: jax>=0.5.0
Requires-Dist: matplotlib>=3.10.0
Requires-Dist: numpy>=2.2.2
Requires-Dist: optax>=0.2.4
Requires-Dist: wandb>=0.19.0
Provides-Extra: docs
Requires-Dist: mkdocs-gen-files==0.5.0; extra == 'docs'
Requires-Dist: mkdocs-jupyter==0.25.1; extra == 'docs'
Requires-Dist: mkdocs-literate-nav==0.6.1; extra == 'docs'
Requires-Dist: mkdocs-material==9.5.47; extra == 'docs'
Requires-Dist: mkdocs==1.6.1; extra == 'docs'
Requires-Dist: mkdocstrings[python]==0.27.0; extra == 'docs'
Requires-Dist: pymdown-extensions==10.12; extra == 'docs'
